{
    "projects": [
        {
            "id": "NFT_Market",
            "projectTitle": "NFT Market",
            "projectDescription": "NFT market place: Buy, sell and transfer NFTs",
            "projectLink": "https://nft-market-psi.vercel.app/",
            "workDone": [
                "Fun little project to learn and practice new technologies"
            ],
            "imgPath": "/images/projects/NFT-market.png",
            "technologies": [
                "React",
                "Next",
                "vercel",
                "Solidity",
                "Typescript",
                "Tailwind"
            ]
        },
        {
            "id": "Language_Service_Solutions",
            "projectTitle": "Language Service Solutions",
            "projectDescription": "LSS has over 20 years of experience providing translation and interpretation services as well as consulting around language services for organizations and communities.",
            "projectLink": "https://languageservicesolutions.com/services",
            "workDone": [
                "Modernized web stack to improve website performance, have better web vitals, and overall modern look and feel",
                "implemented a pixel perfect redesign"
            ],
            "imgPath": "/images/projects/LSS.png",
            "technologies": ["SCSS", "React", "Next", "Vercel"]
        },
        {
            "id": "Bonita_Cafe",
            "projectTitle": "Bonita Cafe",
            "projectDescription": "Colombian Coffee shop part of a restaurant and flower shop franchise",
            "projectLink": "#",
            "workDone": [
                "Design layout",
                "Concept and strategies to increase online sells and brand marketing",
                " Full stack website with a CSM "
            ],
            "imgPath": "/images/projects/Bonita-cafe.png",
            "technologies": ["React", "Next", "vercel", "DatoCMS", "SCSS"]
        }
    ]
}
